pyconsts/__init__.py
pyconstants-0.0.0.dist-info/LICENSE.txt
pyconstants-0.0.0.dist-info/METADATA
pyconstants-0.0.0.dist-info/WHEEL
pyconstants-0.0.0.dist-info/top_level.txt
pyconstants-0.0.0.dist-info/RECORD
