Metadata-Version: 2.1
Name: pyconstants
Version: 0.0.0
Summary: A package that brings constants to python
Home-page: https://github.com/Aurotriz/pyconstants
Author: Aurotriz
Author-email: aurotriz@protonmail.com
License: UNKNOWN
Platform: UNKNOWN
Classifier: Development Status :: 1 - Planning
Classifier: License :: OSI Approved :: Apache Software License
Classifier: Operating System :: OS Independent
